gee_pheno
