Metadata-Version: 1.1
Name: gee-pheno
Version: 0.1.3
Summary: GEE phenology
Home-page: https://github.com/francbartoli/gee_pheno
Author: Francesco Bartoli
Author-email: francesco.bartoli@geobeyond.it
License: MIT license
Keywords: gee_pheno
Platform: UNKNOWN
Classifier: Development Status :: 2 - Pre-Alpha
Classifier: Intended Audience :: Developers
Classifier: License :: OSI Approved :: MIT License
Classifier: Natural Language :: English
Classifier: Programming Language :: Python :: 2
Classifier: Programming Language :: Python :: 2.7
Classifier: Programming Language :: Python :: 3
Classifier: Programming Language :: Python :: 3.4
Classifier: Programming Language :: Python :: 3.5
Classifier: Programming Language :: Python :: 3.6
